w4/__init__.py
w4/w4.py
w4/xy.py
w4-0.1.2.dist-info/LICENSE
w4-0.1.2.dist-info/METADATA
w4-0.1.2.dist-info/WHEEL
w4-0.1.2.dist-info/top_level.txt
w4-0.1.2.dist-info/RECORD
